fcutils.cpython-39-darwin.so
pyfcutils-0.2.4.dist-info/RECORD
pyfcutils-0.2.4.dist-info/LICENSE
pyfcutils-0.2.4.dist-info/WHEEL
pyfcutils-0.2.4.dist-info/top_level.txt
pyfcutils-0.2.4.dist-info/METADATA
