Metadata-Version: 2.1
Name: pyfcutils
Version: 0.2.4
Summary: FlashCam files reader libraries wrapped in Python
Home-page: https://github.com/legend-exp/pyfcutils
Author: Simon Sailer
Author-email: simon.sailer@mpi-hd.mpg.de
Maintainer: The LEGEND collaboration
License: OSL-3.0
Classifier: Development Status :: 4 - Beta
Classifier: Intended Audience :: Developers
Classifier: Intended Audience :: Information Technology
Classifier: Intended Audience :: Science/Research
Classifier: License :: OSI Approved :: Open Software License 3.0 (OSL-3.0)
Classifier: Operating System :: MacOS
Classifier: Operating System :: POSIX
Classifier: Operating System :: Unix
Classifier: Programming Language :: Python
Classifier: Programming Language :: Python :: 3
Classifier: Programming Language :: Python :: 3 :: Only
Classifier: Topic :: Scientific/Engineering
Classifier: Topic :: Scientific/Engineering :: Information Analysis
Classifier: Topic :: Scientific/Engineering :: Mathematics
Classifier: Topic :: Scientific/Engineering :: Physics
Classifier: Topic :: Software Development
Requires-Python: >=3.7
Provides-Extra: test
License-File: LICENSE
